CHANGELOG.rst
LICENSE
MANIFEST.in
README.rst
setup.cfg
setup.py
test/test_api.py
test/test_cmdline.py
timegaps/__init__.py
timegaps/main.py
timegaps/timefilter.py
timegaps/timegaps.py
timegaps.egg-info/PKG-INFO
timegaps.egg-info/SOURCES.txt
timegaps.egg-info/dependency_links.txt
timegaps.egg-info/entry_points.txt
timegaps.egg-info/top_level.txt