Metadata-Version: 1.1
Name: timegaps
Version: 0.1.1
Summary: Accept or reject items based on age categorization.
Home-page: http://gehrcke.de/timegaps
Author: Jan-Philip Gehrcke
Author-email: jgehrcke@googlemail.com
License: UNKNOWN
Keywords: time,categorization,backup,deletion
Platform: POSIX
Platform: Windows
Classifier: Programming Language :: Python
Classifier: Development Status :: 4 - Beta
Classifier: License :: OSI Approved :: MIT License
Classifier: Operating System :: POSIX
Classifier: Operating System :: Microsoft :: Windows
Classifier: Programming Language :: Python :: 2
Classifier: Programming Language :: Python :: 2.7
Classifier: Programming Language :: Python :: 3
Classifier: Programming Language :: Python :: 3.3
Classifier: Programming Language :: Python :: 3.4
Classifier: Topic :: System :: Archiving :: Backup
Classifier: Topic :: System :: Filesystems
Classifier: Topic :: System :: Systems Administration
Classifier: Topic :: Utilities
Classifier: Environment :: Console
Classifier: Intended Audience :: System Administrators
Classifier: Intended Audience :: End Users/Desktop
